longsgis/__init__.py
longsgis/longsgis.py
voronoi_diagram_for_polygons-0.1.9.dist-info/licenses/LICENSE
voronoi_diagram_for_polygons-0.1.9.dist-info/METADATA
voronoi_diagram_for_polygons-0.1.9.dist-info/WHEEL
voronoi_diagram_for_polygons-0.1.9.dist-info/top_level.txt
voronoi_diagram_for_polygons-0.1.9.dist-info/RECORD
