Metadata-Version: 2.4
Name: voronoi-diagram-for-polygons
Version: 0.1.9
Summary: A tool to create Voronoi diagram for polygons.
Home-page: https://github.com/longavailable/voronoi-diagram-for-polygons
Author: Xiaolong "Bruce" Liu, Meixiu Yu
Author-email: liuxiaolong125@gmail.com, meixiuyu@hhu.edu.cn
Classifier: Programming Language :: Python :: 3
Classifier: License :: OSI Approved :: MIT License
Classifier: Operating System :: OS Independent
Requires-Python: >=3.6
License-File: LICENSE
Requires-Dist: shapely>=1.8.dev0
Requires-Dist: geopandas
Requires-Dist: numpy
Dynamic: author
Dynamic: author-email
Dynamic: classifier
Dynamic: description
Dynamic: description-content-type
Dynamic: home-page
Dynamic: license-file
Dynamic: requires-dist
Dynamic: requires-python
Dynamic: summary
